pthelpers/__init__.py
pthelpers/_version.py
pthelpers/core.py
pthelpers/py.typed
pthelpers/fxfilters/__init__.py
pthelpers/fxfilters/fxfilters.py
pthelpers/fxtracers/__init__.py
pthelpers/fxtracers/fxtracers.py
pthelpers/stats/__init__.py
pthelpers/stats/fpops.py
pthelpers/stats/params.py
pthelpers/vis/__init__.py
pthelpers/vis/drawing.py
pthelpers/vis/styles.py
pthelpers-0.1.27.dist-info/LICENSE
pthelpers-0.1.27.dist-info/METADATA
pthelpers-0.1.27.dist-info/WHEEL
pthelpers-0.1.27.dist-info/top_level.txt
pthelpers-0.1.27.dist-info/RECORD
