Metadata-Version: 2.1
Name: pthelpers
Version: 0.1.27
Summary: pthelpers is a is a set of utilities for PyTorch.
Author: Michal Lopuszynski
License: 
Classifier: Programming Language :: Python :: 3
Requires-Python: >=3.10
License-File: LICENSE
Requires-Dist: torch
Requires-Dist: graphviz >=0.20.1
Requires-Dist: tabulate >=0.9.0
